dataformer/__init__.py
dataformer/components/__init__.py
dataformer/components/complexity_scorer.py
dataformer/components/deita.py
dataformer/components/quality_scorer.py
dataformer/components/evol_instruct/__init__.py
dataformer/components/evol_instruct/base.py
dataformer/components/evol_instruct/prompts.py
dataformer/components/evol_quality/__init__.py
dataformer/components/evol_quality/base.py
dataformer/components/evol_quality/prompts.py
dataformer/components/magpie/__init__.py
dataformer/components/magpie/base.py
dataformer/components/magpie/prompts.py
dataformer/components/templates/complexity-scorer.jinja2
dataformer/components/templates/quality-scorer.jinja2
dataformer/llms/__init__.py
dataformer/llms/api_providers.py
dataformer/llms/asyncllm.py
dataformer/utils/__init__.py
dataformer/utils/cache.py
dataformer/utils/data_formats.py
dataformer/utils/notebook.py
dataformer-0.0.2.dist-info/LICENSE
dataformer-0.0.2.dist-info/METADATA
dataformer-0.0.2.dist-info/WHEEL
dataformer-0.0.2.dist-info/top_level.txt
dataformer-0.0.2.dist-info/RECORD
