Metadata-Version: 2.1
Name: dataformer
Version: 0.0.2
Summary: Dataformer is a library to create data for LLMs.
Author-email: Dataformer AI <contact@dataformer.ai>
License: Apache-2.0
Project-URL: Documentation, https://dataformer.ai/
Project-URL: Issues, https://github.com/DataformerAI/dataformer/issues
Project-URL: Source, https://github.com/DataformerAI/dataformer
Keywords: llm,synthetic,data
Classifier: Development Status :: 2 - Pre-Alpha
Classifier: Programming Language :: Python
Classifier: Programming Language :: Python :: 3.8
Classifier: Programming Language :: Python :: 3.9
Classifier: Programming Language :: Python :: 3.10
Classifier: Programming Language :: Python :: 3.11
Classifier: Programming Language :: Python :: 3.12
Classifier: Programming Language :: Python :: Implementation :: CPython
Classifier: Programming Language :: Python :: Implementation :: PyPy
Requires-Python: >=3.8
License-File: LICENSE
Requires-Dist: pydantic>=2.0
Requires-Dist: tiktoken
Requires-Dist: aiohttp
Requires-Dist: python-dotenv
Requires-Dist: pytest
Provides-Extra: dev
Requires-Dist: ruff==0.4.5; extra == "dev"
Requires-Dist: pre-commit>=3.5.0; extra == "dev"
Requires-Dist: black==24.4.2; extra == "dev"
Provides-Extra: openai
Requires-Dist: openai>=1.0.0; extra == "openai"
Provides-Extra: tests
Requires-Dist: pytest>=7.4.0; extra == "tests"
Requires-Dist: pytest-asyncio; extra == "tests"
Requires-Dist: nest-asyncio; extra == "tests"
Requires-Dist: pytest-timeout; extra == "tests"
Requires-Dist: pytest-codspeed; extra == "tests"
